[
  {
    "titulo": "EXEMPLO — Memória Kingston Fury Beast 16GB DDR4 3200MHz",
    "destaque": "Ideal para upgrade de PC Gamer; Dissipador de baixo perfil",
    "preco": "R$ 249,90 à vista",
    "preco_antigo": "R$ 319,90",
    "url": "https://www.amazon.com.br/dp/B097K2NYCB",
    "loja": "amazon",
    "postada": true,
    "obs": "Este é só um modelo. Copie este bloco, cole abaixo, edite os dados e deixe SEM a linha 'postada' para o robô publicar."
  },
  {
    "titulo": "Computador Intel Core 120 16",
    "destaque": "",
    "preco": "R$ 690,79",
    "preco_antigo": "",
    "cupom": "",
    "url": "https://www.promobit.com.br/oferta/computador-intel-core-i5-3470-16gb-ram-ssd-120gb-windows-10-120-gb-16-gb-2926393",
    "loja": "outra",
    "fonte": "https://www.promobit.com.br/oferta/computador-intel-core-i5-3470-16gb-ram-ssd-120gb-windows-10-120-gb-16-gb-2926393",
    "postada": true,
    "postada_em": "2026-07-15 21:40"
  },
  {
    "titulo": "Monitor Gamer ASRock 180Hz, 1ms,",
    "destaque": "",
    "preco": "R$ 899,00",
    "preco_antigo": "",
    "cupom": "",
    "url": "https://www.promobit.com.br/oferta/monitor-gamer-asrock-phantom-27-qhd-180hz-1ms-ips-2926305",
    "loja": "outra",
    "fonte": "https://www.promobit.com.br/oferta/monitor-gamer-asrock-phantom-27-qhd-180hz-1ms-ips-2926305",
    "postada": true,
    "postada_em": "2026-07-15 21:40"
  },
  {
    "titulo": "Water Cooler Husky 360mm Preto",
    "destaque": "",
    "preco": "R$ 199,00",
    "preco_antigo": "",
    "cupom": "",
    "url": "https://www.promobit.com.br/oferta/water-cooler-husky-glacier-argb-360mm-preto-2926216",
    "loja": "outra",
    "fonte": "https://www.promobit.com.br/oferta/water-cooler-husky-glacier-argb-360mm-preto-2926216",
    "postada": true,
    "postada_em": "2026-07-15 21:40"
  },
  {
    "titulo": "Water Cooler Husky 360mm Branco",
    "destaque": "",
    "preco": "R$ 255,00",
    "preco_antigo": "",
    "cupom": "",
    "url": "https://www.promobit.com.br/oferta/water-cooler-husky-icy-comet-argb-360mm-branco-2926215",
    "loja": "outra",
    "fonte": "https://www.promobit.com.br/oferta/water-cooler-husky-icy-comet-argb-360mm-branco-2926215",
    "postada": true,
    "postada_em": "2026-07-15 21:40"
  },
  {
    "titulo": "Cadeira Gamer Fortt Lípsia CGF002-A",
    "destaque": "",
    "preco": "R$ 209,00",
    "preco_antigo": "",
    "cupom": "",
    "url": "https://www.promobit.com.br/oferta/cadeira-gamer-fortt-lipsia-cgf002-a-2925822",
    "loja": "outra",
    "fonte": "https://www.promobit.com.br/oferta/cadeira-gamer-fortt-lipsia-cgf002-a-2925822",
    "postada": true,
    "postada_em": "2026-07-15 21:40"
  },
  {
    "titulo": "Gabinete Gamer Pcyes Branco FANS",
    "destaque": "",
    "preco": "R$ 135,00",
    "preco_antigo": "",
    "cupom": "",
    "url": "https://www.promobit.com.br/oferta/gabinete-gamer-pcyes-forcefield-mini-white-ghost-gffmnwg-branco-sem-fans-2926072",
    "loja": "outra",
    "fonte": "https://www.promobit.com.br/oferta/gabinete-gamer-pcyes-forcefield-mini-white-ghost-gffmnwg-branco-sem-fans-2926072",
    "postada": true,
    "postada_em": "2026-07-15 21:40"
  },
  {
    "titulo": "Monitor Gamer Agon 0,5ms 24",
    "destaque": "",
    "preco": "R$ 492,00",
    "preco_antigo": "",
    "cupom": "",
    "url": "https://www.promobit.com.br/oferta/monitor-gamer-aoc-agon-g50-painel-ips-144-hz-05ms-24-pol-2925343",
    "loja": "outra",
    "fonte": "https://www.promobit.com.br/oferta/monitor-gamer-aoc-agon-g50-painel-ips-144-hz-05ms-24-pol-2925343",
    "postada": true,
    "postada_em": "2026-07-15 21:40"
  },
  {
    "titulo": "Monitor AGON 144Hz 0,5ms",
    "destaque": "",
    "preco": "R$ 509,53",
    "preco_antigo": "",
    "cupom": "",
    "url": "https://www.promobit.com.br/oferta/monitor-aoc-agon-g50-24-144hz-05ms-ips-2925985",
    "loja": "outra",
    "fonte": "https://www.promobit.com.br/oferta/monitor-aoc-agon-g50-24-144hz-05ms-ips-2925985",
    "postada": true,
    "postada_em": "2026-07-15 21:41"
  },
  {
    "titulo": "Controle 8BitDo Ultimate Star Rail)",
    "destaque": "",
    "preco": "R$ 256,16",
    "preco_antigo": "",
    "cupom": "",
    "url": "https://www.promobit.com.br/oferta/controle-sem-fio-8bitdo-ultimate-2-para-pc-e-android-evernight-licenciado-oficialmente-por-honkai-star-rail-2925972",
    "loja": "outra",
    "fonte": "https://www.promobit.com.br/oferta/controle-sem-fio-8bitdo-ultimate-2-para-pc-e-android-evernight-licenciado-oficialmente-por-honkai-star-rail-2925972",
    "postada": true,
    "postada_em": "2026-07-15 21:41"
  },
  {
    "titulo": "Cooler Digital Ag620 Deepcool Preto",
    "destaque": "",
    "preco": "R$ 279,90",
    "preco_antigo": "",
    "cupom": "",
    "url": "https://www.promobit.com.br/oferta/air-cooler-digital-ag620-deepcool-preto-2925887",
    "loja": "outra",
    "fonte": "https://www.promobit.com.br/oferta/air-cooler-digital-ag620-deepcool-preto-2925887",
    "postada": true,
    "postada_em": "2026-07-15 21:41"
  }
]